google_colab_selenium/__init__.py
google_colab_selenium/chromedriver.py
google_colab_selenium/colab_selenium_manager.py
google_colab_selenium/exceptions.py
google_colab_selenium/spinner.py
google_colab_selenium/undetected_chromedriver.py
google_colab_selenium-1.0.16.dist-info/licenses/LICENSE
google_colab_selenium-1.0.16.dist-info/METADATA
google_colab_selenium-1.0.16.dist-info/PKG-INFO 2
google_colab_selenium-1.0.16.dist-info/SOURCES 2.txt
google_colab_selenium-1.0.16.dist-info/WHEEL
google_colab_selenium-1.0.16.dist-info/dependency_links 2.txt
google_colab_selenium-1.0.16.dist-info/requires 2.txt
google_colab_selenium-1.0.16.dist-info/top_level 2.txt
google_colab_selenium-1.0.16.dist-info/top_level.txt
google_colab_selenium-1.0.16.dist-info/RECORD
