Metadata-Version: 2.4
Name: google-colab-selenium
Version: 1.0.16
Summary: Easily use Selenium in Google Colab Notebooks!
Author: Jacob Padilla
License: MIT
Project-URL: Homepage, https://github.com/jpjacobpadilla/Google-Colab-Selenium
Keywords: selenium,google-colab,webdriver,automation,chromedriver
Requires-Python: >=3.7
License-File: LICENSE
Requires-Dist: notebook>=6.5.7
Requires-Dist: selenium
Provides-Extra: undetected
Requires-Dist: undetected-chromedriver; extra == "undetected"
Dynamic: license-file
